quantpiler-0.3.5.dist-info/METADATA
quantpiler-0.3.5.dist-info/WHEEL
quantpiler-0.3.5.dist-info/license_files/LICENSE
quantpiler/__init__.py
quantpiler/quantpiler.cpython-312-x86_64-linux-gnu.so
quantpiler-0.3.5.dist-info/RECORD
