Metadata-Version: 2.1
Name: quantpiler
Version: 0.3.5
Classifier: License :: OSI Approved :: GNU Affero General Public License v3 or later (AGPLv3+)
Classifier: Development Status :: 3 - Alpha
Classifier: Intended Audience :: Science/Research
Classifier: Operating System :: Microsoft :: Windows
Classifier: Operating System :: POSIX :: Linux
Classifier: Topic :: Scientific/Engineering
Classifier: Programming Language :: Rust
Classifier: Programming Language :: Python :: Implementation :: CPython
Classifier: Programming Language :: Python :: Implementation :: PyPy
Requires-Dist: qiskit >=0.40
License-File: LICENSE
Summary: Сompiler of classical algorithms into oracles for quantum computing
Keywords: qiskit,quantum
Author: Alexander Averyanov <alex@averyan.ru>
Author-email: Alexander Averyanov <alex@averyan.ru>
License: AGPL-3.0-or-later
Requires-Python: >=3.8
Project-URL: Source Code, https://github.com/averyanalex/quantpiler
